logmate/__init__.py
logmate/cli.py
logmate/logmate.py
logmate-0.1.2.dist-info/LICENSE
logmate-0.1.2.dist-info/METADATA
logmate-0.1.2.dist-info/WHEEL
logmate-0.1.2.dist-info/entry_points.txt
logmate-0.1.2.dist-info/top_level.txt
logmate-0.1.2.dist-info/RECORD
